MANIFEST.in
Readme.md
dev-requirements.frozen.txt
dev-requirements.txt
licence.txt
noxfile.py
requirements.frozen.txt
requirements.txt
setup.cfg
setup.py
pandas_ml_common/__init__.py
pandas_ml_common.egg-info/PKG-INFO
pandas_ml_common.egg-info/SOURCES.txt
pandas_ml_common.egg-info/dependency_links.txt
pandas_ml_common.egg-info/requires.txt
pandas_ml_common.egg-info/top_level.txt
pandas_ml_common/__pycache__/__init__.cpython-37.pyc
pandas_ml_common/__pycache__/__init__.cpython-38.pyc
pandas_ml_common/decorator/__init__.py
pandas_ml_common/decorator/multi_frame_decorator.py
pandas_ml_common/decorator/__pycache__/__init__.cpython-37.pyc
pandas_ml_common/decorator/__pycache__/__init__.cpython-38.pyc
pandas_ml_common/decorator/__pycache__/multi_frame_decorator.cpython-37.pyc
pandas_ml_common/decorator/__pycache__/multi_frame_decorator.cpython-38.pyc
pandas_ml_common/df_monkey_patch/__init__.py
pandas_ml_common/df_monkey_patch/df_values.py
pandas_ml_common/df_monkey_patch/__pycache__/__init__.cpython-37.pyc
pandas_ml_common/df_monkey_patch/__pycache__/__init__.cpython-38.pyc
pandas_ml_common/df_monkey_patch/__pycache__/df_values.cpython-37.pyc
pandas_ml_common/df_monkey_patch/__pycache__/df_values.cpython-38.pyc
pandas_ml_common/sampling/__init__.py
pandas_ml_common/sampling/cross_validation.py
pandas_ml_common/sampling/sampler.py
pandas_ml_common/sampling/splitter.py
pandas_ml_common/sampling/__pycache__/__init__.cpython-37.pyc
pandas_ml_common/sampling/__pycache__/__init__.cpython-38.pyc
pandas_ml_common/sampling/__pycache__/cross_validation.cpython-37.pyc
pandas_ml_common/sampling/__pycache__/cross_validation.cpython-38.pyc
pandas_ml_common/sampling/__pycache__/sampler.cpython-37.pyc
pandas_ml_common/sampling/__pycache__/sampler.cpython-38.pyc
pandas_ml_common/sampling/__pycache__/splitter.cpython-37.pyc
pandas_ml_common/sampling/__pycache__/splitter.cpython-38.pyc
pandas_ml_common/utils/__init__.py
pandas_ml_common/utils/callable_utils.py
pandas_ml_common/utils/column_lagging_utils.py
pandas_ml_common/utils/index_utils.py
pandas_ml_common/utils/jupyther_utils.py
pandas_ml_common/utils/lazy_value.py
pandas_ml_common/utils/logging_utils.py
